scikit_network-0.33.4.dist-info/RECORD
scikit_network-0.33.4.dist-info/WHEEL
scikit_network-0.33.4.dist-info/top_level.txt
scikit_network-0.33.4.dist-info/METADATA
scikit_network-0.33.4.dist-info/licenses/LICENSE
scikit_network-0.33.4.dist-info/licenses/AUTHORS.rst
sknetwork/log.py
sknetwork/__init__.py
sknetwork/test_log.py
sknetwork/test_base.py
sknetwork/sknetwork.py
sknetwork/base.py
sknetwork/classification/metrics.py
sknetwork/classification/vote.pyx
sknetwork/classification/diffusion.py
sknetwork/classification/__init__.py
sknetwork/classification/base_rank.py
sknetwork/classification/propagation.py
sknetwork/classification/vote.cpython-39-darwin.so
sknetwork/classification/pagerank.py
sknetwork/classification/base.py
sknetwork/classification/vote.cpp
sknetwork/classification/knn.py
sknetwork/classification/tests/test_metrics.py
sknetwork/classification/tests/__init__.py
sknetwork/classification/tests/test_pagerank.py
sknetwork/classification/tests/test_diffusion.py
sknetwork/classification/tests/test_knn.py
sknetwork/classification/tests/test_API.py
sknetwork/classification/tests/test_propagation.py
sknetwork/visualization/dendrograms.py
sknetwork/visualization/__init__.py
sknetwork/visualization/graphs.py
sknetwork/visualization/colors.py
sknetwork/visualization/tests/test_graphs.py
sknetwork/visualization/tests/__init__.py
sknetwork/visualization/tests/test_dendrograms.py
sknetwork/topology/cliques.cpython-39-darwin.so
sknetwork/topology/weisfeiler_lehman_core.cpython-39-darwin.so
sknetwork/topology/core.cpp
sknetwork/topology/cliques.pyx
sknetwork/topology/triangles.cpp
sknetwork/topology/minheap.pyx
sknetwork/topology/weisfeiler_lehman_core.pyx
sknetwork/topology/minheap.cpython-39-darwin.so
sknetwork/topology/__init__.py
sknetwork/topology/triangles.cpython-39-darwin.so
sknetwork/topology/cycles.py
sknetwork/topology/weisfeiler_lehman.py
sknetwork/topology/core.cpython-39-darwin.so
sknetwork/topology/minheap.pxd
sknetwork/topology/structure.py
sknetwork/topology/cliques.cpp
sknetwork/topology/minheap.cpp
sknetwork/topology/triangles.pyx
sknetwork/topology/weisfeiler_lehman_core.cpp
sknetwork/topology/core.pyx
sknetwork/topology/tests/test_cycles.py
