Metadata-Version: 2.4
Name: scikit-network
Version: 0.33.4
Summary: Graph algorithms
Author: Scikit-network team
Maintainer-email: Thomas Bonald <bonald@enst.fr>
License: BSD License
Project-URL: Repository, https://github.com/sknetwork-team/scikit-network
Project-URL: Documentation, https://scikit-network.readthedocs.io/
Project-URL: Changelog, https://github.com/sknetwork-team/scikit-network/blob/master/HISTORY.rst
Keywords: sknetwork
Classifier: Development Status :: 3 - Alpha
Classifier: Intended Audience :: Developers
Classifier: Intended Audience :: Information Technology
Classifier: Intended Audience :: Education
Classifier: Intended Audience :: Science/Research
Classifier: License :: OSI Approved :: BSD License
Classifier: Natural Language :: English
Classifier: Programming Language :: Cython
Classifier: Programming Language :: Python :: 3.9
Classifier: Programming Language :: Python :: 3.10
Classifier: Programming Language :: Python :: 3.11
Classifier: Programming Language :: Python :: 3.12
Classifier: Programming Language :: Python :: 3.13
Requires-Python: >=3.9
License-File: LICENSE
License-File: AUTHORS.rst
Requires-Dist: numpy>=1.22.4
Requires-Dist: scipy>=1.7.3
Provides-Extra: test
Requires-Dist: pytest; extra == "test"
Requires-Dist: note; extra == "test"
Requires-Dist: pluggy>=0.7.1; extra == "test"
Dynamic: license-file
